llama_index/readers/upstage/__init__.py
llama_index/readers/upstage/base.py
llama_index/readers/upstage/document_parse.py
llama_index_readers_upstage-0.4.1.dist-info/METADATA
llama_index_readers_upstage-0.4.1.dist-info/WHEEL
llama_index_readers_upstage-0.4.1.dist-info/licenses/LICENSE
llama_index_readers_upstage-0.4.1.dist-info/RECORD
