Metadata-Version: 2.4
Name: llama-index-readers-upstage
Version: 0.4.1
Summary: llama-index readers upstage integration
Author-email: JunKeon Park <junkeon@upstage.ai>
License-Expression: AGPL-3.0
License-File: LICENSE
Requires-Python: <4.0,>=3.9
Requires-Dist: llama-index-core<0.15,>=0.13.0
Requires-Dist: pymupdf<2,>=1.23.21
